nano_dev_utils/__init__.py
nano_dev_utils/__version__.py
nano_dev_utils/_constants.py
nano_dev_utils/common.py
nano_dev_utils/dynamic_importer.py
nano_dev_utils/release_ports.py
nano_dev_utils/timers.py
nano_dev_utils-1.7.0.dist-info/METADATA
nano_dev_utils-1.7.0.dist-info/WHEEL
nano_dev_utils-1.7.0.dist-info/licenses/LICENSE
nano_dev_utils-1.7.0.dist-info/RECORD
