Metadata-Version: 2.4
Name: nano_dev_utils
Version: 1.7.0
Summary: A collection of small Python utilities for developers.
Project-URL: Homepage, https://github.com/yaronday/nano_utils
Project-URL: Issues, https://github.com/yaronday/nano_utils/issues
Project-URL: license, https://github.com/yaronday/nano_dev_utils/blob/master/LICENSE
Author-email: Yaron Dayan <yaronday77@gmail.com>
License: MIT
License-File: LICENSE
Classifier: Operating System :: OS Independent
Classifier: Programming Language :: Python :: 3
Requires-Python: >=3.10
Requires-Dist: build>=1.3.0
